{
    "version": "0.1.35",
    "architecture": {
        "32bit": {
            "url": "https://github.com/stacc/blocc-cli-releases/releases/download/v0.1.35/blocc_0.1.35_Windows_i386.tar.gz",
            "bin": [
                "blocc.exe"
            ],
            "hash": "df4633c0c5b803abde49dc863f36eea0e594805f6e0c40df7ab11fcaa09c47c0"
        },
        "64bit": {
            "url": "https://github.com/stacc/blocc-cli-releases/releases/download/v0.1.35/blocc_0.1.35_Windows_x86_64.tar.gz",
            "bin": [
                "blocc.exe"
            ],
            "hash": "361aecd642232fcb2ba48cc821ff7fa3a06b40f01f96793195f3eabf82c4b5da"
        }
    },
    "homepage": "https://github.com/stacc/blocc-cli-releases",
    "license": "Apache-2.0",
    "description": "Software used to communicate with Stacc cloud environments"
}